ssh_commander/__init__.py
ssh_commander/_version.py
ssh_commander/ssh_commander.py
ssh_commander/ssh_key_helper.py
ssh_commander/ssh_session.py
ssh_commander-0.3.data/scripts/_version.py
ssh_commander-0.3.dist-info/LICENSE
ssh_commander-0.3.dist-info/METADATA
ssh_commander-0.3.dist-info/WHEEL
ssh_commander-0.3.dist-info/entry_points.txt
ssh_commander-0.3.dist-info/top_level.txt
ssh_commander-0.3.dist-info/RECORD
