Metadata-Version: 2.1
Name: ssh-commander
Version: 0.3
Summary: Excecute commands on several remote hosts, with SSH
Home-page: https://github.com/tuxedoar/ssh-commander
Author: tuxedoar
Author-email: tuxedoar@gmail.com
License: GPLv3
Platform: UNKNOWN
Classifier: Programming Language :: Python :: 3 :: Only
Classifier: Programming Language :: Python :: 3.7
Classifier: License :: OSI Approved :: GNU General Public License v3 (GPLv3)
Classifier: Operating System :: OS Independent
Classifier: Intended Audience :: System Administrators
Classifier: Environment :: Console
Requires-Python: >=3.7
Requires-Dist: paramiko
Requires-Dist: colorama
Requires-Dist: coloredlogs
